[
    {
        "key": "dbln",
        "value": "%7B%2261574973969010%22%3A%22zTI25mq6%22%7D",
        "domain": "facebook.com",
        "path": "/login/device-based/",
        "hostOnly": false,
        "creation": "2025-08-11T12:31:02.849Z",
        "lastAccessed": "2025-08-11T12:31:02.850Z"
    },
    {
        "key": "datr",
        "value": "-HaIaJi9tU6Zh69yaXoLrOy8",
        "domain": "facebook.com",
        "path": "/",
        "hostOnly": false,
        "creation": "2025-08-11T12:31:02.850Z",
        "lastAccessed": "2025-08-11T12:31:02.850Z"
    },
    {
        "key": "sb",
        "value": "-HaIaNpWvc8RyDLJqVmdIyUT",
        "domain": "facebook.com",
        "path": "/",
        "hostOnly": false,
        "creation": "2025-08-11T12:31:02.850Z",
        "lastAccessed": "2025-08-11T12:31:02.850Z"
    },
    {
        "key": "ps_l",
        "value": "1",
        "domain": "facebook.com",
        "path": "/",
        "hostOnly": false,
        "creation": "2025-08-11T12:31:02.850Z",
        "lastAccessed": "2025-08-11T12:31:02.850Z"
    },
    {
        "key": "ps_n",
        "value": "1",
        "domain": "facebook.com",
        "path": "/",
        "hostOnly": false,
        "creation": "2025-08-11T12:31:02.850Z",
        "lastAccessed": "2025-08-11T12:31:02.850Z"
    },
    {
        "key": "pas",
        "value": "61574973969010%3ACKyNeOGTjH",
        "domain": "facebook.com",
        "path": "/",
        "hostOnly": false,
        "creation": "2025-08-11T12:31:02.850Z",
        "lastAccessed": "2025-08-11T12:31:02.850Z"
    },
    {
        "key": "vpd",
        "value": "v1%3B793x412x2.625",
        "domain": "facebook.com",
        "path": "/",
        "hostOnly": false,
        "creation": "2025-08-11T12:31:02.850Z",
        "lastAccessed": "2025-08-11T12:31:02.850Z"
    },
    {
        "key": "locale",
        "value": "en_GB",
        "domain": "facebook.com",
        "path": "/",
        "hostOnly": false,
        "creation": "2025-08-11T12:31:02.850Z",
        "lastAccessed": "2025-08-11T12:31:02.850Z"
    },
    {
        "key": "c_user",
        "value": "61574973969010",
        "domain": "facebook.com",
        "path": "/",
        "hostOnly": false,
        "creation": "2025-08-11T12:31:02.850Z",
        "lastAccessed": "2025-08-11T12:31:02.850Z"
    },
    {
        "key": "xs",
        "value": "30%3AqmnDUIA5WONpzA%3A2%3A1754749353%3A-1%3A-1",
        "domain": "facebook.com",
        "path": "/",
        "hostOnly": false,
        "creation": "2025-08-11T12:31:02.851Z",
        "lastAccessed": "2025-08-11T12:31:02.851Z"
    },
    {
        "key": "wd",
        "value": "980x1885",
        "domain": "facebook.com",
        "path": "/",
        "hostOnly": false,
        "creation": "2025-08-11T12:31:02.851Z",
        "lastAccessed": "2025-08-11T12:31:02.851Z"
    },
    {
        "key": "dpr",
        "value": "2.625",
        "domain": "facebook.com",
        "path": "/",
        "hostOnly": false,
        "creation": "2025-08-11T12:31:02.851Z",
        "lastAccessed": "2025-08-11T12:31:02.851Z"
    },
    {
        "key": "fr",
        "value": "0syuQcxK6dIZX91Sl.AWclpgIwqSQt5gU2KHPsAHSAs65dHonCElw1LaxOfbyeMtg-4eE.BoiHb4..AAA.0.0.BomeJ6.AWcywU4gyPjreAplU51XcETXgw4",
        "domain": "facebook.com",
        "path": "/",
        "hostOnly": false,
        "creation": "2025-08-11T12:31:02.851Z",
        "lastAccessed": "2025-08-11T12:31:02.851Z"
    },
    {
        "key": "fbl_st",
        "value": "101415499%3BT%3A29248590",
        "domain": "facebook.com",
        "path": "/",
        "hostOnly": false,
        "creation": "2025-08-11T12:31:02.851Z",
        "lastAccessed": "2025-08-11T12:31:02.851Z"
    },
    {
        "key": "wl_cbv",
        "value": "v2%3Bclient_version%3A2889%3Btimestamp%3A1754915450",
        "domain": "facebook.com",
        "path": "/",
        "hostOnly": false,
        "creation": "2025-08-11T12:31:02.851Z",
        "lastAccessed": "2025-08-11T12:31:02.851Z"
    }
]
